{
  "version": "1.0",
  "total": 0,
  "tools inspection": {
    "Code Inspection": 0
  },
  "linter": "QDJVM",
  "attributes": {
    "deviceId": "200820300000000-199c-c7f7-efe0-98f5c461790c",
    "jobUrl": "",
    "vcs": {
      "sarifIdea": {
        "repositoryUri": "https://github.com/asyncapi/kotlin-asyncapi",
        "revisionId": "49ce8090842799cd4067a4d6d9d1b8e05fea57c8",
        "branch": "master"
      }
    },
    "repoUrl": "https://github.com/asyncapi/kotlin-asyncapi"
  },
  "linterVersion": "253.31510"
}